odoo/addons/tms_sale/README.rst
odoo/addons/tms_sale/__init__.py
odoo/addons/tms_sale/__manifest__.py
odoo/addons/tms_sale/i18n/tms_sale.pot
odoo/addons/tms_sale/models/__init__.py
odoo/addons/tms_sale/models/sale_order.py
odoo/addons/tms_sale/models/sale_order_line.py
odoo/addons/tms_sale/models/seat_ticket.py
odoo/addons/tms_sale/models/tms_order.py
odoo/addons/tms_sale/security/ir.model.access.csv
odoo/addons/tms_sale/static/description/icon.png
odoo/addons/tms_sale/static/description/icon.svg
odoo/addons/tms_sale/static/src/js/line_ticket_wizard_controller.esm.js
odoo/addons/tms_sale/static/src/js/line_trip_wizard_controller.esm.js
odoo/addons/tms_sale/static/src/js/sale_order_line_product_field.esm.js
odoo/addons/tms_sale/views/product_template_views.xml
odoo/addons/tms_sale/views/sale_order_views.xml
odoo/addons/tms_sale/views/seat_ticket_views.xml
odoo/addons/tms_sale/views/tms_order_views.xml
odoo/addons/tms_sale/wizard/__init__.py
odoo/addons/tms_sale/wizard/sale_order_line_trip.py
odoo/addons/tms_sale/wizard/sale_order_line_trip_views.xml
odoo/addons/tms_sale/wizard/seat_ticket_line.py
odoo/addons/tms_sale/wizard/seat_ticket_line_views.xml
odoo_addon_tms_sale-17.0.1.0.1.dist-info/METADATA
odoo_addon_tms_sale-17.0.1.0.1.dist-info/WHEEL
odoo_addon_tms_sale-17.0.1.0.1.dist-info/top_level.txt
odoo_addon_tms_sale-17.0.1.0.1.dist-info/RECORD
